module_inventory_binder/__init__.py
module_inventory_binder/admin.py
module_inventory_binder/forms.py
module_inventory_binder/models.py
module_inventory_binder/navigation.py
module_inventory_binder/signals.py
module_inventory_binder/urls.py
module_inventory_binder/views.py
module_inventory_binder/migrations/0001_initial.py
module_inventory_binder/migrations/__init__.py
module_inventory_binder/templates/module_inventory_binder/module_inventory_binding_form.html
module_inventory_binder/templates/module_inventory_binder/module_inventory_binding_list.html
module_inventory_binder-1.4.0.dist-info/LICENSE
module_inventory_binder-1.4.0.dist-info/METADATA
module_inventory_binder-1.4.0.dist-info/WHEEL
module_inventory_binder-1.4.0.dist-info/top_level.txt
module_inventory_binder-1.4.0.dist-info/RECORD
