Metadata-Version: 2.1
Name: module-inventory-binder
Version: 1.4.0
Summary: A NetBox plugin to manually bind modules with inventory items.
Home-page: https://github.com/yourusername/module_inventory_binder
Author: Viktor Kubec
Author-email: Viktor.Kubec@gmail.com
License: MIT
Platform: UNKNOWN
Classifier: Development Status :: 5 - Production/Stable
Classifier: Framework :: Django
Classifier: Framework :: Django :: 3.1
Classifier: Intended Audience :: Developers
Classifier: License :: OSI Approved :: MIT License
Classifier: Programming Language :: Python :: 3
Classifier: Programming Language :: Python :: 3.10
Classifier: Topic :: Software Development :: Libraries :: Python Modules
License-File: LICENSE
